[1,["ecpdLyjvZBwrvm+cedCcQy","cfYBCB4ldKqKT7jSlBiOGx","a2MjXRFdtLlYQ5ouAFv/+R","2a/1RjV5BEhbhl2+mr9qN+","e1y57luuVN9psZpRHQT9vS","b2t5mK795BZaAlaN03TRTg","a15hi4nshLu6mPyQ1m6CzT","4bqjFnqKlGdILDCgBpzZ4w"],["node","_spriteFrame","_parent","root","videoBtn","closeBtn","actNode","bg","data","_defaultClip","_textureSetter"],[["cc.Node",["_name","_groupIndex","_opacity","_components","_prefab","_contentSize","_children","_parent","_trs","_color"],0,9,4,5,2,1,7,5],["cc.Node",["_name","_children","_components","_prefab","_contentSize","_trs","_parent"],2,2,12,4,5,7,1],["cc.PrefabInfo",["fileId","root"],2,1],["cc.Sprite",["_sizeMode","node","_materials","_spriteFrame"],2,1,3,6],["cc.Layout",["_resize","_N$layoutType","_N$paddingBottom","_N$spacingX","node","_layoutSize"],-1,1,5],"cc.SpriteFrame",["cc.Prefab",["_name"],2],["9aac252wnVBHog9CrubcU6z",["node","bg","actNode","closeBtn","videoBtn"],3,1,1,1,1,1],["cc.Widget",["_alignFlags","_originalWidth","_originalHeight","node"],0,1],["cc.BlockInputEvents",["node"],3,1],["220c7tM+jZEHa7lZGHLQAIV",["node"],3,1],["cc.Animation",["playOnLoad","node","_clips","_defaultClip"],2,1,3,6],["cc.Label",["_string","_N$horizontalAlign","_N$verticalAlign","node","_materials"],0,1,3],["cc.LabelOutline",["_width","node","_color"],2,1,5],["cc.Button",["node"],3,1]],[[2,0,1,2],[0,0,7,3,4,5,8,2],[3,1,2,3,1],[3,0,1,2,3,2],[12,0,1,2,3,4,4],[13,0,1,2,2],[14,0,1],[6,0,2],[0,0,1,6,3,4,5,3],[0,0,2,1,7,3,4,9,5,4],[0,0,1,7,6,3,4,5,3],[0,0,6,3,4,5,8,2],[0,0,7,6,3,4,5,8,2],[1,0,1,2,3,4,5,2],[1,0,6,1,2,3,4,5,2],[7,0,1,2,3,4,1],[2,1,1],[8,0,1,2,3,4],[9,0,1],[10,0,1],[11,0,1,2,3,2],[4,0,1,2,4,5,4],[4,0,1,3,4,5,4]],[[[[7,"dia_foxDate"],[8,"dia_foxDate",2,[-7,-8],[[15,-6,-5,-4,-3,-2]],[16,-1],[5,720,1280]],[9,"bg",168,2,1,[[3,0,-9,[0],1],[17,45,720,1280,-10],[18,-11],[19,-12]],[0,"77c7B/FRFL7JrD9ItY813X",1],[4,4278190080],[5,720,1280]],[13,"anniu",[-16,-17],[[[2,-13,[8],9],[20,true,-14,[11],10],-15],4,4,1],[0,"24J3oqKmpLFpoEvVYc1QMU",1],[5,227,88],[151,0,0,0,0,0,1,1,1,0]],[10,"actNode",2,1,[-19],[[21,1,2,260,-18,[5,0,974]]],[0,"dfyIDTBchMo64Q1hzcsGEw",1],[5,0,974]],[11,"btns",[-21,3],[[22,1,1,75,-20,[5,529,84]]],[0,"50YRcAsWlPO5YsXwdqUiqC",1],[5,529,84],[-14,-390.447,0,0,0,0,1,1,1,1]],[14,"anniu3",5,[-24],[[[2,-22,[3],4],-23],4,1],[0,"adgFjLc0FPPbFRoM3WebOu",1],[5,227,88],[-151,0,0,0,0,0,1,1,1,0]],[12,"xct",4,[5],[[3,0,-25,[12],13]],[0,"5cpPk95QlLPbuQcXV2yBOy",1],[5,720,714],[0,130,0,0,0,0,1,1,1,1]],[1,"New Label",6,[[4,"下次一定",1,1,-26,[2]],[5,2,-27,[4,536870912]]],[0,"359EILADFMVrBqmLAA/mJn",1],[5,164,54.4],[0,5.532,0,0,0,0,1,1,1,1]],[1,"New Label",3,[[4,"接 受",1,1,-28,[7]],[5,2,-29,[4,536870912]]],[0,"cb9cxu12tEl78IkwvGU5VQ",1],[5,95.11,54.4],[25.353,5.532,0,0,0,0,1,1,1,1]],[6,6],[1,"shipin",3,[[2,-30,[5],6]],[0,"0deQRRTdRNhanBFyjE2/7X",1],[5,41,30],[-58.424,0,0,0,0,0,1,1,1,1]],[6,3]],0,[0,3,1,0,4,12,0,5,10,0,6,4,0,7,2,0,0,1,0,-1,2,0,-2,4,0,0,2,0,0,2,0,0,2,0,0,2,0,0,3,0,0,3,0,-3,12,0,-1,11,0,-2,9,0,0,4,0,-1,7,0,0,5,0,-1,6,0,0,6,0,-2,10,0,-1,8,0,0,7,0,0,8,0,0,8,0,0,9,0,0,9,0,0,11,0,8,1,3,2,5,5,2,7,30],[0,0,0,0,0,0,0,0,0,0,0,0,0,0],[-1,1,-1,-1,1,-1,1,-1,-1,1,9,-1,-1,1],[0,2,0,0,3,0,4,0,0,5,1,1,0,6]],[[{"name":"aidadi","rect":[0,7,720,714],"offset":[0,0],"originalSize":[720,728],"capInsets":[0,0,0,0]}],[5],0,[0],[10],[7]]]]